<?xml version="1.0" encoding="ISO-8859-1" ?>
<REGION class="grphdr1" id="region-5" name="SOUTH CAROLINA, outer coast-cont."><LOCATION class="stationname region-5 sub_region-8">Folly Island (outer coast)</LOCATION><LOCATION class="stationname region-5 sub_region-8">Folly River Bridge, Flooy Island</LOCATION><LOCATION class="stationname region-5 sub_region-8">Folly Creek, Hwy. 171 bridge</LOCATION><LOCATION class="stationname region-5 sub_region-8">Folly River, north, Folly Island</LOCATION><LOCATION class="stationname region-5 sub_region-9">Snake Island</LOCATION><LOCATION class="stationname region-5 sub_region-9">Abbapoola Creek entrance</LOCATION><LOCATION class="stationname region-5 sub_region-9">Elliott Cut entrance</LOCATION><LOCATION class="stationname region-5 sub_region-9">Pennys Creek, west entrance</LOCATION><LOCATION class="stationname region-5 sub_region-9">Sandblasters, Pennys Creek</LOCATION><LOCATION class="stationname region-5 sub_region-9">Limehouse Bridge</LOCATION><LOCATION class="stationname region-5 sub_region-9">Church Flats</LOCATION><LOCATION class="stationname region-5 sub_region-9">Kiawah River Bridge</LOCATION><LOCATION class="stationname region-5 sub_region-10">Ocella Creek, 2 mi. above entrance</LOCATION><LOCATION class="stationname region-5 sub_region-10">Rockville, Bohicket Creek</LOCATION><LOCATION class="stationname region-5 sub_region-10">Ho-Non-Wah Boy Scout Camp, Bohicket Creek</LOCATION><LOCATION class="stationname region-5 sub_region-10">Oak Branch, Bohicket Creek</LOCATION><LOCATION class="stationname region-5 sub_region-10">Point of Pines</LOCATION><LOCATION class="stationname region-5 sub_region-10">Leadenwah Creek, 3 mi. above entrance</LOCATION><LOCATION class="stationname region-5 sub_region-10">Steamboat Landing, Steamboat Creek</LOCATION><LOCATION class="stationname region-5 sub_region-10">Windsor Plantation, Russel Creek</LOCATION><LOCATION class="stationname region-5 sub_region-10">Dawho Bridge, Dawho River</LOCATION><LOCATION class="stationname region-5 sub_region-10">Park Island, Tom Point Creek</LOCATION><LOCATION class="stationname region-5 sub_region-10">Toogoodoo Creek, 2 mi. above entrance</LOCATION><LOCATION class="stationname region-5 sub_region-10">Lower Toogoodoo Creek, 2 mi. above entrance</LOCATION><LOCATION class="stationname region-5 sub_region-11">Bluff Point</LOCATION><LOCATION class="stationname region-5 sub_region-11">Yonges Island</LOCATION><LOCATION class="stationname region-5 sub_region-11">Johns Island, Church Creek</LOCATION><LOCATION class="stationname region-5 sub_region-11">Church Creek bridge</LOCATION><LOCATION class="stationname region-5 sub_region-11">Edisto Beach, Edisto Island</LOCATION><LOCATION class="stationname region-5 sub_region-12">Edisto Marina, Big Bay Creek entrance</LOCATION><LOCATION class="stationname region-5 sub_region-12">Carters Dock, Big Bay Creek</LOCATION><LOCATION class="stationname region-5 sub_region-12">Peters Point, St. Pierre Creek</LOCATION><LOCATION class="stationname region-5 sub_region-12">Fenwick Island</LOCATION><LOCATION class="stationname region-5 sub_region-12">Pine Landing</LOCATION><LOCATION class="stationname region-5 sub_region-12">Dawho River</LOCATION><LOCATION class="stationname region-5 sub_region-12">Willtown Bluff, Edisto River</LOCATION><LOCATION class="stationname region-5 sub_region-12">Hope Creek, Edisto River</LOCATION><LOCATION class="stationname region-5 sub_region-12">Penny Creek, south of, Edisto River</LOCATION><LOCATION class="stationname region-5 sub_region-12">Jacksonboro Camp</LOCATION><LOCATION class="stationname region-5 sub_region-12">Canaday Landing, south of, Edisto River</LOCATION></REGION>
